lasertools_pulsenlo
