Metadata-Version: 2.1
Name: lasertools-pulsenlo
Version: 0.0.1.1
Summary: A module to apply simplified nonlinear processes to a pulse
Home-page: https://github.com/lasertools/lasertools_pulsenlo
Author: brittonm
Author-email: 68578865+brittonm@users.noreply.github.com
License: GPLv3
Download-URL: https://github.com/lasertools/lasertools_pulsenlo/archive/refs/tags/v_0_0_1_1.tar.gz
Platform: UNKNOWN
Classifier: Programming Language :: Python :: 3.9
License-File: LICENSE
